hwa/__init__.py
hwa/data/template/header.html
hwa/data/template/hwa_repo.html
hwa/data/template/index.html
hwa/data/template/ingestion_form.html
hwa/data/template/status_msg.html
hwa/data/template/doc/hwa_use.html
hwa/data/template/doc/magen_overview.html
hwa/data/template/doc/policy_administration.html
hwa/data/template/helpers/footer.html
hwa/data/template/helpers/stylesheets.html
hwa/hwa_server/__init__.py
hwa/hwa_server/hwa_crypt.py
hwa/hwa_server/hwa_events.py
hwa/hwa_server/hwa_server.py
hwa/hwa_server/hwa_urls.py
hwa/hwa_server/hwa_utils.py
magen_hwa_service-1.1a1.data/scripts/hwa_server.py
magen_hwa_service-1.1a1.data/scripts/magen_svc_cfgfile_gen.sh
magen_hwa_service-1.1a1.dist-info/DESCRIPTION.rst
magen_hwa_service-1.1a1.dist-info/METADATA
magen_hwa_service-1.1a1.dist-info/RECORD
magen_hwa_service-1.1a1.dist-info/WHEEL
magen_hwa_service-1.1a1.dist-info/metadata.json
magen_hwa_service-1.1a1.dist-info/top_level.txt
